git_tracker/__init__.py
git_tracker/__main__.py
git_tracker/core.py
git_tracker-0.1.3.dist-info/METADATA
git_tracker-0.1.3.dist-info/WHEEL
git_tracker-0.1.3.dist-info/entry_points.txt
git_tracker-0.1.3.dist-info/RECORD
