Metadata-Version: 2.1
Name: git-tracker
Version: 0.1.3
Summary: A tool to aggregate and export git logs
Author: Jacob Valdez
Author-email: jacobfv123@gmail.com
Requires-Python: >=3.11,<4.0
Classifier: Programming Language :: Python :: 3
Classifier: Programming Language :: Python :: 3.11
Classifier: Programming Language :: Python :: 3.12
Requires-Dist: anthropic (>=0.34.2,<0.35.0)
Requires-Dist: ell-ai (>=0.0.5,<0.0.6)
Requires-Dist: markdown (>=3.7,<4.0)
Requires-Dist: openai (>=1.45.0,<2.0.0)
Requires-Dist: pydantic (>=2.9.1,<3.0.0)
Requires-Dist: typer (>=0.12.5,<0.13.0)
